django_querysetsequence-0.18.dist-info/licenses/LICENSE
queryset_sequence/__init__.py
queryset_sequence/pagination.py
django_querysetsequence-0.18.dist-info/METADATA
django_querysetsequence-0.18.dist-info/WHEEL
django_querysetsequence-0.18.dist-info/top_level.txt
django_querysetsequence-0.18.dist-info/RECORD
