Metadata-Version: 2.4
Name: django-querysetsequence
Version: 0.18
Summary: Chain together multiple (disparate) QuerySets to treat them as a single QuerySet.
Home-page: https://github.com/clokep/django-querysetsequence
Author: Patrick Cloke
Author-email: clokep@patrick.cloke.us
License: ISC
Project-URL: Documentation, https://django-querysetsequence.readthedocs.io
Project-URL: Release notes, https://github.com/clokep/django-querysetsequence/blob/main/CHANGELOG.rst
Project-URL: Source, https://github.com/clokep/django-querysetsequence
Project-URL: Funding, https://github.com/sponsors/clokep
Project-URL: Tracker, https://github.com/clokep/django-querysetsequence/issues
Keywords: django,queryset,chain,multi,multiple,iterable
Classifier: Development Status :: 4 - Beta
Classifier: Intended Audience :: Developers
Classifier: Topic :: Software Development :: Libraries :: Python Modules
Classifier: Environment :: Web Environment
Classifier: Topic :: Internet
Classifier: Framework :: Django
Classifier: Framework :: Django :: 4.2
Classifier: Framework :: Django :: 5.1
Classifier: Framework :: Django :: 5.2
Classifier: Programming Language :: Python
Classifier: Programming Language :: Python :: 3.9
Classifier: Programming Language :: Python :: 3.10
Classifier: Programming Language :: Python :: 3.11
Classifier: Programming Language :: Python :: 3.12
Classifier: Programming Language :: Python :: 3.13
Classifier: License :: OSI Approved :: ISC License (ISCL)
Requires-Python: >=3.9
License-File: LICENSE
Requires-Dist: django>=4.2
Dynamic: license-file
